shutil_ext/__about__.py
shutil_ext/__init__.py
shutil_ext/py.typed
shutil_ext-0.1.0.dist-info/METADATA
shutil_ext-0.1.0.dist-info/WHEEL
shutil_ext-0.1.0.dist-info/licenses/LICENSE
shutil_ext-0.1.0.dist-info/RECORD
